<?xml version="1.0" encoding="UTF-8"?>
<MetaDataObject xmlns="http://v8.1c.ru/8.3/MDClasses" xmlns:app="http://v8.1c.ru/8.2/managed-application/core" xmlns:cfg="http://v8.1c.ru/8.1/data/enterprise/current-config" xmlns:cmi="http://v8.1c.ru/8.2/managed-application/cmi" xmlns:ent="http://v8.1c.ru/8.1/data/enterprise" xmlns:lf="http://v8.1c.ru/8.2/managed-application/logform" xmlns:style="http://v8.1c.ru/8.1/data/ui/style" xmlns:sys="http://v8.1c.ru/8.1/data/ui/fonts/system" xmlns:v8="http://v8.1c.ru/8.1/data/core" xmlns:v8ui="http://v8.1c.ru/8.1/data/ui" xmlns:web="http://v8.1c.ru/8.1/data/ui/colors/web" xmlns:win="http://v8.1c.ru/8.1/data/ui/colors/windows" xmlns:xen="http://v8.1c.ru/8.3/xcf/enums" xmlns:xpr="http://v8.1c.ru/8.3/xcf/predef" xmlns:xr="http://v8.1c.ru/8.3/xcf/readable" xmlns:xs="http://www.w3.org/2001/XMLSchema" xmlns:xsi="http://www.w3.org/2001/XMLSchema-instance" version="2.0">
	<Catalog uuid="4f198712-a3d1-4a2d-af89-7f5d4505480c">
		<InternalInfo>
			<xr:GeneratedType name="CatalogObject.ПараметрыШагов" category="Object">
				<xr:TypeId>b7424c5c-b641-4082-b11b-a8674b914054</xr:TypeId>
				<xr:ValueId>395ed685-463d-4407-b805-b99e705e3e83</xr:ValueId>
			</xr:GeneratedType>
			<xr:GeneratedType name="CatalogRef.ПараметрыШагов" category="Ref">
				<xr:TypeId>582520c0-12d1-48cc-9988-fe3a97c43bee</xr:TypeId>
				<xr:ValueId>541a859b-744a-4280-83ac-a092bb640a85</xr:ValueId>
			</xr:GeneratedType>
			<xr:GeneratedType name="CatalogSelection.ПараметрыШагов" category="Selection">
				<xr:TypeId>a38e04a2-eeb4-4517-b28c-9186e6f33f67</xr:TypeId>
				<xr:ValueId>e6830982-fb82-4eb5-9957-842ea744fd6d</xr:ValueId>
			</xr:GeneratedType>
			<xr:GeneratedType name="CatalogList.ПараметрыШагов" category="List">
				<xr:TypeId>956a27ac-a40e-4975-9cb2-13ea42c7bee3</xr:TypeId>
				<xr:ValueId>ff4135a9-8b2e-4a35-b36b-b256e7e5ddad</xr:ValueId>
			</xr:GeneratedType>
			<xr:GeneratedType name="CatalogManager.ПараметрыШагов" category="Manager">
				<xr:TypeId>86ae7e54-ea92-4cfd-ab60-7c82a1634c7f</xr:TypeId>
				<xr:ValueId>6afc34e5-93fe-4042-9aa4-79b73fa772d0</xr:ValueId>
			</xr:GeneratedType>
		</InternalInfo>
		<Properties>
			<Name>ПараметрыШагов</Name>
			<Synonym>
				<v8:item>
					<v8:lang>ru</v8:lang>
					<v8:content>Параметры шагов</v8:content>
				</v8:item>
			</Synonym>
			<Comment/>
			<Hierarchical>true</Hierarchical>
			<HierarchyType>HierarchyFoldersAndItems</HierarchyType>
			<LimitLevelCount>false</LimitLevelCount>
			<LevelCount>2</LevelCount>
			<FoldersOnTop>true</FoldersOnTop>
			<UseStandardCommands>true</UseStandardCommands>
			<Owners/>
			<SubordinationUse>ToItems</SubordinationUse>
			<CodeLength>9</CodeLength>
			<DescriptionLength>100</DescriptionLength>
			<CodeType>String</CodeType>
			<CodeAllowedLength>Variable</CodeAllowedLength>
			<CodeSeries>WholeCatalog</CodeSeries>
			<CheckUnique>true</CheckUnique>
			<Autonumbering>true</Autonumbering>
			<DefaultPresentation>AsDescription</DefaultPresentation>
			<Characteristics/>
			<PredefinedDataUpdate>Auto</PredefinedDataUpdate>
			<EditType>InDialog</EditType>
			<QuickChoice>false</QuickChoice>
			<ChoiceMode>BothWays</ChoiceMode>
			<InputByString>
				<xr:Field>Catalog.ПараметрыШагов.StandardAttribute.Description</xr:Field>
				<xr:Field>Catalog.ПараметрыШагов.StandardAttribute.Code</xr:Field>
			</InputByString>
			<SearchStringModeOnInputByString>Begin</SearchStringModeOnInputByString>
			<FullTextSearchOnInputByString>DontUse</FullTextSearchOnInputByString>
			<ChoiceDataGetModeOnInputByString>Directly</ChoiceDataGetModeOnInputByString>
			<DefaultObjectForm>Catalog.ПараметрыШагов.Form.ФормаЭлемента</DefaultObjectForm>
			<DefaultFolderForm/>
			<DefaultListForm/>
			<DefaultChoiceForm>Catalog.ПараметрыШагов.Form.ФормаВыбора</DefaultChoiceForm>
			<DefaultFolderChoiceForm/>
			<AuxiliaryObjectForm/>
			<AuxiliaryFolderForm/>
			<AuxiliaryListForm/>
			<AuxiliaryChoiceForm/>
			<AuxiliaryFolderChoiceForm/>
			<IncludeHelpInContents>false</IncludeHelpInContents>
			<BasedOn/>
			<DataLockFields/>
			<DataLockControlMode>Managed</DataLockControlMode>
			<FullTextSearch>Use</FullTextSearch>
			<ObjectPresentation/>
			<ExtendedObjectPresentation/>
			<ListPresentation/>
			<ExtendedListPresentation/>
			<Explanation/>
			<CreateOnInput>Use</CreateOnInput>
			<ChoiceHistoryOnInput>Auto</ChoiceHistoryOnInput>
		</Properties>
		<ChildObjects>
			<Attribute uuid="4e97fe5b-f526-4837-9968-6cf879f38193">
				<Properties>
					<Name>ТипПараметра</Name>
					<Synonym>
						<v8:item>
							<v8:lang>ru</v8:lang>
							<v8:content>Тип параметра</v8:content>
						</v8:item>
					</Synonym>
					<Comment/>
					<Type>
						<v8:Type>cfg:EnumRef.ТипыПараметров</v8:Type>
					</Type>
					<PasswordMode>false</PasswordMode>
					<Format/>
					<EditFormat/>
					<ToolTip/>
					<MarkNegatives>false</MarkNegatives>
					<Mask/>
					<MultiLine>false</MultiLine>
					<ExtendedEdit>false</ExtendedEdit>
					<MinValue xsi:nil="true"/>
					<MaxValue xsi:nil="true"/>
					<FillFromFillingValue>false</FillFromFillingValue>
					<FillValue xsi:nil="true"/>
					<FillChecking>ShowError</FillChecking>
					<ChoiceFoldersAndItems>Items</ChoiceFoldersAndItems>
					<ChoiceParameterLinks/>
					<ChoiceParameters/>
					<QuickChoice>Auto</QuickChoice>
					<CreateOnInput>Auto</CreateOnInput>
					<ChoiceForm/>
					<LinkByType/>
					<ChoiceHistoryOnInput>Auto</ChoiceHistoryOnInput>
					<Use>ForItem</Use>
					<Indexing>DontIndex</Indexing>
					<FullTextSearch>Use</FullTextSearch>
				</Properties>
			</Attribute>
			<Attribute uuid="f8a2d16e-df7d-4a3e-84e7-4ca767d3f247">
				<Properties>
					<Name>ЗначениеПараметра</Name>
					<Synonym>
						<v8:item>
							<v8:lang>ru</v8:lang>
							<v8:content>Значение параметра</v8:content>
						</v8:item>
					</Synonym>
					<Comment/>
					<Type>
						<v8:Type>xs:string</v8:Type>
						<v8:StringQualifiers>
							<v8:Length>0</v8:Length>
							<v8:AllowedLength>Variable</v8:AllowedLength>
						</v8:StringQualifiers>
					</Type>
					<PasswordMode>false</PasswordMode>
					<Format/>
					<EditFormat/>
					<ToolTip/>
					<MarkNegatives>false</MarkNegatives>
					<Mask/>
					<MultiLine>false</MultiLine>
					<ExtendedEdit>false</ExtendedEdit>
					<MinValue xsi:nil="true"/>
					<MaxValue xsi:nil="true"/>
					<FillFromFillingValue>false</FillFromFillingValue>
					<FillValue xsi:type="xs:string"/>
					<FillChecking>DontCheck</FillChecking>
					<ChoiceFoldersAndItems>Items</ChoiceFoldersAndItems>
					<ChoiceParameterLinks/>
					<ChoiceParameters/>
					<QuickChoice>Auto</QuickChoice>
					<CreateOnInput>Auto</CreateOnInput>
					<ChoiceForm/>
					<LinkByType/>
					<ChoiceHistoryOnInput>Auto</ChoiceHistoryOnInput>
					<Use>ForItem</Use>
					<Indexing>DontIndex</Indexing>
					<FullTextSearch>Use</FullTextSearch>
				</Properties>
			</Attribute>
			<Form>ФормаЭлемента</Form>
			<Form>ФормаВыбора</Form>
		</ChildObjects>
	</Catalog>
</MetaDataObject>